result/design.sv
// Code your design here
`timescale 1ns / 1ps
//////////////////////////////////////////////////////////////////////////////////
// Company: 
// Engineer: 
// 
// Create Date: 31.03.2026 16:47:26
// Design Name: 
// Module Name: risc_core
// Project Name: 
// Target Devices: 
// Tool Versions: 
// Description: 
// 
// Dependencies: 
// 
// Revision:
// Revision 0.01 - File Created
// Additional Comments:
// 
//////////////////////////////////////////////////////////////////////////////////


`default_nettype none
`timescale 1ns/1ps

module riscv_core #(
    parameter integer RV32M = 1,
    parameter integer RV32E = 0
)(
    input  wire        clk,
    input  wire        resetb,
    input  wire        stall,

    // Interrupt sources
    input  wire        timer_irq,
    input  wire        sw_irq,
    input  wire        ext_irq,

    // Memory interface - instruction
    input  wire        imem_valid,
    input  wire [31:0] imem_rdata,
    output reg  [31:0] imem_addr,
    output wire        imem_ready,

    // Memory interface - data
    input  wire        dmem_rvalid,
    input  wire [31:0] dmem_rdata,
    output reg  [31:0] dmem_raddr,
    output reg  [31:0] dmem_wdata,
    output reg  [31:0] dmem_waddr,
    output reg  [3:0]  dmem_wstrb,
    output wire        dmem_rready,
    output wire        dmem_wready
);
assign imem_ready = !stall;
assign dmem_rready  = 1'b1;
assign dmem_wready  = 1'b1;
localparam NOP = 32'h00000013;  // ADDI x0, x0, 0
localparam RESETVEC = 32'h00000000;

always @(posedge clk or negedge resetb) begin
    if (!resetb) begin
        imem_addr   <= RESETVEC;
        dmem_raddr  <= 32'd0;
        dmem_waddr  <= 32'd0;
        dmem_wdata  <= 32'd0;
        dmem_wstrb  <= 4'd0;
    end else if (!stall) begin
        // For now, just increment PC for testing
        imem_addr <= imem_addr + 4;
        dmem_raddr <= dmem_raddr + 4;
        // write ports stay 0 for now
    end
end

// ────────────── Instruction opcode constants ───────────────
localparam OP_LUI    = 7'b0110111;
localparam OP_AUIPC  = 7'b0010111;
localparam OP_JAL    = 7'b1101111;
localparam OP_JALR   = 7'b1100111;
localparam OP_BRANCH = 7'b1100011;
localparam OP_LOAD   = 7'b0000011;
localparam OP_STORE  = 7'b0100011;
localparam OP_ARITHI = 7'b0010011;
localparam OP_ARITHR = 7'b0110011;
localparam OP_SYSTEM = 7'b1110011;

// funct3 constants
localparam F3_ADD_SUB = 3'b000;
localparam F3_SLL     = 3'b001;
localparam F3_SLT     = 3'b010;
localparam F3_SLTU    = 3'b011;
localparam F3_XOR     = 3'b100;
localparam F3_OR      = 3'b110;
localparam F3_AND     = 3'b111;
localparam F3_SR      = 3'b101;  // SRLI/SRAI

// ────────────── Pipeline registers ───────────────
reg [31:0] pc_fetch, pc_id, pc_ex, pc_wb;
reg [31:0] ex_insn, ex_imm;
reg [4:0]  ex_rs1, ex_rs2, ex_rd;
reg [2:0]  ex_fn3;
reg        ex_fn7_alt, ex_store, ex_load, ex_alu_op, ex_mul_op;
reg        ex_lui, ex_auipc, ex_jal, ex_jalr, ex_branch, ex_sys, ex_sys_any;
reg        ex_illegal;

reg stall_q, flush_q;
reg exception;

// ────────────── Register file ───────────────
localparam RF_DEPTH = (RV32E==1) ? 16 : 32;
reg [31:0] rf [RF_DEPTH-1:1];

// ────────────── Memory handshake ───────────────
assign dmem_rready = ex_load;
assign dmem_wready = ex_store;

// ────────────── Fetch logic ───────────────
always @(posedge clk or negedge resetb) begin
    if(!resetb) begin
        pc_fetch <= RESETVEC;
        pc_id <= RESETVEC;
    end else if(!stall) begin
        pc_fetch <= pc_fetch + 4;
        pc_id <= pc_fetch;
    end
end

// ────────────── Immediate decode ───────────────
always @* begin
    ex_imm = 32'd0;
    if(!stall_q) begin
        case (imem_rdata[6:0])
            OP_LUI, OP_AUIPC: ex_imm = {imem_rdata[31:12],12'd0};
            OP_JAL:          ex_imm = {{12{imem_rdata[31]}}, imem_rdata[19:12], imem_rdata[20], imem_rdata[30:21],1'b0};
            OP_JALR, OP_LOAD, OP_ARITHI: ex_imm = {{20{imem_rdata[31]}}, imem_rdata[31:20]};
            OP_BRANCH:       ex_imm = {{20{imem_rdata[31]}}, imem_rdata[7], imem_rdata[30:25], imem_rdata[11:8],1'b0};
            OP_STORE:        ex_imm = {{20{imem_rdata[31]}}, imem_rdata[31:25], imem_rdata[11:7]};
        endcase
    end
end

// ────────────── ID → EX pipeline ───────────────
always @(posedge clk or negedge resetb) begin
    if(!resetb) begin
        ex_insn <= NOP; ex_rs1 <= 0; ex_rs2 <= 0; ex_rd <= 0;
        ex_fn3 <= 0; ex_store <= 0; ex_load <= 0; ex_alu_op <= 0;
        ex_mul_op <= 0; ex_lui <= 0; ex_auipc <= 0; ex_jal <= 0; ex_jalr <= 0;
        ex_branch <= 0; ex_sys <= 0; ex_sys_any <= 0; ex_illegal <= 0;
        flush_q <= 1;
        stall_q <= 1;
        exception <= 0;
    end else if(!stall) begin
        ex_insn <= imem_rdata;
        ex_rs1 <= imem_rdata[19:15];
        ex_rs2 <= imem_rdata[24:20];
        ex_rd  <= imem_rdata[11:7];
        ex_fn3 <= imem_rdata[14:12];
        ex_store <= (imem_rdata[6:0]==OP_STORE);
        ex_load  <= (imem_rdata[6:0]==OP_LOAD);
        ex_alu_op <= (imem_rdata[6:0]==OP_ARITHI) || (imem_rdata[6:0]==OP_ARITHR);
        ex_mul_op <= (RV32M==1) && (imem_rdata[6:0]==OP_ARITHR) && (imem_rdata[31:25]==7'h01);
        ex_lui <= (imem_rdata[6:0]==OP_LUI);
        ex_auipc <= (imem_rdata[6:0]==OP_AUIPC);
        ex_jal <= (imem_rdata[6:0]==OP_JAL);
        ex_jalr <= (imem_rdata[6:0]==OP_JALR);
        ex_branch <= (imem_rdata[6:0]==OP_BRANCH);
        ex_sys <= (imem_rdata[6:0]==OP_SYSTEM) && (imem_rdata[14:12]==3'b000);
        ex_sys_any <= (imem_rdata[6:0]==OP_SYSTEM);
        ex_illegal <= 0; // Can implement illegal instruction detection if needed
        flush_q <= 0;
        stall_q <= 0;
    end
end

// ────────────── ALU (EX stage) ───────────────
wire [31:0] alu_a = (ex_rs1==0) ? 0 : rf[ex_rs1];
wire [31:0] alu_b = ex_alu_op ? ((ex_fn3==F3_SR)? {{27{1'b0}}, ex_insn[24:20]} : ex_imm) : (ex_rs2==0 ? 0 : rf[ex_rs2]);
reg  [31:0] alu_out;

always @* begin
    alu_out = 32'd0;
    if(ex_alu_op) begin
        case(ex_fn3)
            F3_ADD_SUB: alu_out = alu_a + alu_b;
            F3_AND:     alu_out = alu_a & alu_b;
            F3_OR:      alu_out = alu_a | alu_b;
            F3_XOR:     alu_out = alu_a ^ alu_b;
            F3_SLL:     alu_out = alu_a << alu_b[4:0];
            F3_SR:      alu_out = alu_a >> alu_b[4:0]; // SRLI (arithmetic shift not handled here)
            default:    alu_out = alu_a + alu_b;
        endcase
    end else if(ex_lui) alu_out = ex_imm;
    else if(ex_auipc) alu_out = pc_id + ex_imm;
    else if(ex_jal || ex_jalr) alu_out = pc_id + 4;
end

// ────────────── WB stage ───────────────
always @(posedge clk) begin
    if(!stall) begin
        if(ex_rd != 0) rf[ex_rd] <= alu_out;
    end
end

endmodule

result/testbench.sv
// Code your testbench here
// or browse Examples
`timescale 1ns/1ps
`default_nettype none

module tb_riscv_core();

    reg clk;
    reg resetb;
    reg stall;

    reg  timer_irq, sw_irq, ext_irq;

    reg  [31:0] imem_rdata;
    reg  imem_valid;
    wire [31:0] imem_addr;
    wire imem_ready;

    reg  [31:0] dmem_rdata;
    reg  dmem_rvalid;
    wire [31:0] dmem_raddr;
    wire [31:0] dmem_wdata;
    wire [31:0] dmem_waddr;
    wire [3:0]  dmem_wstrb;
    wire        dmem_rready;
    wire        dmem_wready;

    // Instantiate the core
    riscv_core uut (
        .clk(clk),
        .resetb(resetb),
        .stall(stall),
        .timer_irq(timer_irq),
        .sw_irq(sw_irq),
        .ext_irq(ext_irq),
        .imem_valid(imem_valid),
        .imem_rdata(imem_rdata),
        .imem_addr(imem_addr),
        .imem_ready(imem_ready),
        .dmem_rvalid(dmem_rvalid),
        .dmem_rdata(dmem_rdata),
        .dmem_raddr(dmem_raddr),
        .dmem_wdata(dmem_wdata),
        .dmem_waddr(dmem_waddr),
        .dmem_wstrb(dmem_wstrb),
        .dmem_rready(dmem_rready),
        .dmem_wready(dmem_wready)
    );

    // Clock
    initial clk = 0;
    always #5 clk = ~clk;

    // ---- Mock memory interface ----
    assign dmem_rready = 1;  // Data read always ready
    assign dmem_wready = 1;  // Data write always ready

    // Provide some dummy data for reads
    always @(posedge clk) begin
        if (dmem_rvalid) begin
            dmem_rdata <= 32'hDEADBEEF;  // Example dummy data
        end
    end

    // Monitor writes
    always @(posedge clk) begin
        if (dmem_wready && |dmem_wstrb) begin
            $display("Write: addr=%h data=%h strb=%b", dmem_waddr, dmem_wdata, dmem_wstrb);
        end
    end

    // ---- Test sequence ----
    initial begin
         $dumpfile("dump.vcd");   // VCD filename
    $dumpvars(0, tb_riscv_core); // Dump all signals in the testbench and instantiated modules
        // Initialize signals
        resetb = 0;
        stall = 0;
        timer_irq = 0; sw_irq = 0; ext_irq = 0;
        imem_rdata = 32'h00000013; // NOP
        imem_valid = 1;
        dmem_rvalid = 0;

        // Apply reset
        #20 resetb = 1;

        // Feed a few instructions
        #10 imem_rdata = 32'b00010010001101000101000010110111; // LUI x1,0x12345
        #10 imem_rdata = 32'b00000000010100001000000110010011; // ADDI x3,x1,5
        #10 imem_rdata = 32'b00000000001100001000001010110011; // ADD x4,x1,x3
        #10 imem_rdata = 32'b00000000001100001001001010110011; // OR x5,x1,x3

        // Dummy data memory read
        #10 dmem_rvalid = 1;
        #10 dmem_rvalid = 0;

        // Finish simulation
        #50;
        $display("Simulation finished");
        $finish;
    end

endmodule

result/dump.vcd
$version Generated by VerilatedVcd $end
$timescale 1ps $end
 $scope module tb_riscv_core $end
  $var wire 1 g clk $end
  $var wire 1 # resetb $end
  $var wire 1 $ stall $end
  $var wire 1 % timer_irq $end
  $var wire 1 & sw_irq $end
  $var wire 1 ' ext_irq $end
  $var wire 32 ( imem_rdata [31:0] $end
  $var wire 1 ) imem_valid $end
  $var wire 32 , imem_addr [31:0] $end
  $var wire 1 * imem_ready $end
  $var wire 32 C dmem_rdata [31:0] $end
  $var wire 1 + dmem_rvalid $end
  $var wire 32 - dmem_raddr [31:0] $end
  $var wire 32 c dmem_wdata [31:0] $end
  $var wire 32 d dmem_waddr [31:0] $end
  $var wire 4 e dmem_wstrb [3:0] $end
  $var wire 1 l dmem_rready $end
  $var wire 1 l dmem_wready $end
  $scope module uut $end
   $var wire 32 m RV32M [31:0] $end
   $var wire 32 n RV32E [31:0] $end
   $var wire 1 g clk $end
   $var wire 1 # resetb $end
   $var wire 1 $ stall $end
   $var wire 1 % timer_irq $end
   $var wire 1 & sw_irq $end
   $var wire 1 ' ext_irq $end
   $var wire 1 ) imem_valid $end
   $var wire 32 ( imem_rdata [31:0] $end
   $var wire 32 , imem_addr [31:0] $end
   $var wire 1 * imem_ready $end
   $var wire 1 + dmem_rvalid $end
   $var wire 32 C dmem_rdata [31:0] $end
   $var wire 32 - dmem_raddr [31:0] $end
   $var wire 32 c dmem_wdata [31:0] $end
   $var wire 32 d dmem_waddr [31:0] $end
   $var wire 4 e dmem_wstrb [3:0] $end
   $var wire 1 l dmem_rready $end
   $var wire 1 l dmem_wready $end
   $var wire 32 o NOP [31:0] $end
   $var wire 32 p RESETVEC [31:0] $end
   $var wire 7 q OP_LUI [6:0] $end
   $var wire 7 r OP_AUIPC [6:0] $end
   $var wire 7 s OP_JAL [6:0] $end
   $var wire 7 t OP_JALR [6:0] $end
   $var wire 7 u OP_BRANCH [6:0] $end
   $var wire 7 v OP_LOAD [6:0] $end
   $var wire 7 w OP_STORE [6:0] $end
   $var wire 7 x OP_ARITHI [6:0] $end
   $var wire 7 y OP_ARITHR [6:0] $end
   $var wire 7 z OP_SYSTEM [6:0] $end
   $var wire 3 { F3_ADD_SUB [2:0] $end
   $var wire 3 | F3_SLL [2:0] $end
   $var wire 3 } F3_SLT [2:0] $end
   $var wire 3 ~ F3_SLTU [2:0] $end
   $var wire 3 !! F3_XOR [2:0] $end
   $var wire 3 "! F3_OR [2:0] $end
   $var wire 3 #! F3_AND [2:0] $end
   $var wire 3 $! F3_SR [2:0] $end
   $var wire 32 . pc_fetch [31:0] $end
   $var wire 32 / pc_id [31:0] $end
   $var wire 32 %! pc_ex [31:0] $end
   $var wire 32 &! pc_wb [31:0] $end
   $var wire 32 0 ex_insn [31:0] $end
   $var wire 32 h ex_imm [31:0] $end
   $var wire 5 1 ex_rs1 [4:0] $end
   $var wire 5 2 ex_rs2 [4:0] $end
   $var wire 5 f ex_rd [4:0] $end
   $var wire 3 3 ex_fn3 [2:0] $end
   $var wire 1 '! ex_fn7_alt $end
   $var wire 1 4 ex_store $end
   $var wire 1 5 ex_load $end
   $var wire 1 6 ex_alu_op $end
   $var wire 1 7 ex_mul_op $end
   $var wire 1 8 ex_lui $end
   $var wire 1 9 ex_auipc $end
   $var wire 1 : ex_jal $end
   $var wire 1 ; ex_jalr $end
   $var wire 1 < ex_branch $end
   $var wire 1 = ex_sys $end
   $var wire 1 > ex_sys_any $end
   $var wire 1 ? ex_illegal $end
   $var wire 1 @ stall_q $end
   $var wire 1 A flush_q $end
   $var wire 1 B exception $end
   $var wire 32 (! RF_DEPTH [31:0] $end
   $var wire 32 D rf[1] [31:0] $end
   $var wire 32 E rf[2] [31:0] $end
   $var wire 32 F rf[3] [31:0] $end
   $var wire 32 G rf[4] [31:0] $end
   $var wire 32 H rf[5] [31:0] $end
   $var wire 32 I rf[6] [31:0] $end
   $var wire 32 J rf[7] [31:0] $end
   $var wire 32 K rf[8] [31:0] $end
   $var wire 32 L rf[9] [31:0] $end
   $var wire 32 M rf[10] [31:0] $end
   $var wire 32 N rf[11] [31:0] $end
   $var wire 32 O rf[12] [31:0] $end
   $var wire 32 P rf[13] [31:0] $end
   $var wire 32 Q rf[14] [31:0] $end
   $var wire 32 R rf[15] [31:0] $end
   $var wire 32 S rf[16] [31:0] $end
   $var wire 32 T rf[17] [31:0] $end
   $var wire 32 U rf[18] [31:0] $end
   $var wire 32 V rf[19] [31:0] $end
   $var wire 32 W rf[20] [31:0] $end
   $var wire 32 X rf[21] [31:0] $end
   $var wire 32 Y rf[22] [31:0] $end
   $var wire 32 Z rf[23] [31:0] $end
   $var wire 32 [ rf[24] [31:0] $end
   $var wire 32 \ rf[25] [31:0] $end
   $var wire 32 ] rf[26] [31:0] $end
   $var wire 32 ^ rf[27] [31:0] $end
   $var wire 32 _ rf[28] [31:0] $end
   $var wire 32 ` rf[29] [31:0] $end
   $var wire 32 a rf[30] [31:0] $end
   $var wire 32 b rf[31] [31:0] $end
   $var wire 32 i alu_a [31:0] $end
   $var wire 32 j alu_b [31:0] $end
   $var wire 32 k alu_out [31:0] $end
  $upscope $end
 $upscope $end
$enddefinitions $end


#0
0#
0$
0%
0&
0'
b00000000000000000000000000010011 (
1)
1*
0+
b00000000000000000000000000000000 ,
b00000000000000000000000000000000 -
b00000000000000000000000000000000 .
b00000000000000000000000000000000 /
b00000000000000000000000000000000 0
b00000 1
b00000 2
b000 3
04
05
06
07
08
09
0:
0;
0<
0=
0>
0?
0@
0A
0B
b00000000000000000000000000000000 C
b00000000000000000000000000000000 D
b00000000000000000000000000000000 E
b00000000000000000000000000000000 F
b00000000000000000000000000000000 G
b00000000000000000000000000000000 H
b00000000000000000000000000000000 I
b00000000000000000000000000000000 J
b00000000000000000000000000000000 K
b00000000000000000000000000000000 L
b00000000000000000000000000000000 M
b00000000000000000000000000000000 N
b00000000000000000000000000000000 O
b00000000000000000000000000000000 P
b00000000000000000000000000000000 Q
b00000000000000000000000000000000 R
b00000000000000000000000000000000 S
b00000000000000000000000000000000 T
b00000000000000000000000000000000 U
b00000000000000000000000000000000 V
b00000000000000000000000000000000 W
b00000000000000000000000000000000 X
b00000000000000000000000000000000 Y
b00000000000000000000000000000000 Z
b00000000000000000000000000000000 [
b00000000000000000000000000000000 \
b00000000000000000000000000000000 ]
b00000000000000000000000000000000 ^
b00000000000000000000000000000000 _
b00000000000000000000000000000000 `
b00000000000000000000000000000000 a
b00000000000000000000000000000000 b
b00000000000000000000000000000000 c
b00000000000000000000000000000000 d
b0000 e
b00000 f
0g
b00000000000000000000000000000000 h
b00000000000000000000000000000000 i
b00000000000000000000000000000000 j
b00000000000000000000000000000000 k
1l
b00000000000000000000000000000001 m
b00000000000000000000000000000000 n
b00000000000000000000000000010011 o
b00000000000000000000000000000000 p
b0110111 q
b0010111 r
b1101111 s
b1100111 t
b1100011 u
b0000011 v
b0100011 w
b0010011 x
b0110011 y
b1110011 z
b000 {
b001 |
b010 }
b011 ~
b100 !!
b110 "!
b111 #!
b101 $!
b00000000000000000000000000000000 %!
b00000000000000000000000000000000 &!
0'!
b00000000000000000000000000100000 (!
#5000
b00000000000000000000000000010011 0
1@
1A
1g
#10000
0g
#15000
1g
#20000
1#
0g
#25000
b00000000000000000000000000000100 ,
b00000000000000000000000000000100 -
b00000000000000000000000000000100 .
16
0@
0A
1g
#30000
b00010010001101000101000010110111 (
0g
b00010010001101000101000000000000 h
b00010010001101000101000000000000 j
b00010010001101000101000000000000 k
#35000
b00000000000000000000000000001000 ,
b00000000000000000000000000001000 -
b00000000000000000000000000001000 .
b00000000000000000000000000000100 /
b00010010001101000101000010110111 0
b01000 1
b00011 2
b101 3
06
18
b00001 f
1g
b00000000000000000000000000000000 j
#40000
b00000000010100001000000110010011 (
0g
b00000000000000000000000000000101 h
b00000000000000000000000000000101 k
#45000
b00000000000000000000000000001100 ,
b00000000000000000000000000001100 -
b00000000000000000000000000001100 .
b00000000000000000000000000001000 /
b00000000010100001000000110010011 0
b00001 1
b00101 2
b000 3
16
08
b00000000000000000000000000000101 D
b00011 f
1g
b00000000000000000000000000000101 i
b00000000000000000000000000000101 j
b00000000000000000000000000001010 k
#50000
b00000000001100001000001010110011 (
0g
b00000000000000000000000000000000 h
b00000000000000000000000000000000 j
b00000000000000000000000000000101 k
#55000
b00000000000000000000000000010000 ,
b00000000000000000000000000010000 -
b00000000000000000000000000010000 .
b00000000000000000000000000001100 /
b00000000001100001000001010110011 0
b00011 2
b00000000000000000000000000000101 F
b00101 f
1g
#60000
b00000000001100001001001010110011 (
0g
#65000
b00000000000000000000000000010100 ,
b00000000000000000000000000010100 -
b00000000000000000000000000010100 .
b00000000000000000000000000010000 /
b00000000001100001001001010110011 0
b001 3
b00000000000000000000000000000101 H
1g
#70000
1+
0g
#75000
b00000000000000000000000000011000 ,
b00000000000000000000000000011000 -
b00000000000000000000000000011000 .
b00000000000000000000000000010100 /
b11011110101011011011111011101111 C
1g
#80000
0+
0g
#85000
b00000000000000000000000000011100 ,
b00000000000000000000000000011100 -
b00000000000000000000000000011100 .
b00000000000000000000000000011000 /
1g
#90000
0g
#95000
b00000000000000000000000000100000 ,
b00000000000000000000000000100000 -
b00000000000000000000000000100000 .
b00000000000000000000000000011100 /
1g
#100000
0g
#105000
b00000000000000000000000000100100 ,
b00000000000000000000000000100100 -
b00000000000000000000000000100100 .
b00000000000000000000000000100000 /
1g
#110000
0g
#115000
b00000000000000000000000000101000 ,
b00000000000000000000000000101000 -
b00000000000000000000000000101000 .
b00000000000000000000000000100100 /
1g
#120000
0g
#125000
b00000000000000000000000000101100 ,
b00000000000000000000000000101100 -
b00000000000000000000000000101100 .
b00000000000000000000000000101000 /
1g
